 [
    {
        "name": "ENC_L_FROM_ACU",
        "topic": "A",
        "priority": 7,
        "sending": ["ECU"],
        "receiving": ["STEER", "BMS_HV"],
        "contents": {
            "current": "uint16",
            "status": ["OFF", "PRECHARGE", "ON", "FATAL"]
        }
    },{
        "name": "ENC_R_FROM_ACU",
        "topic": "A",
        "priority":3,
        "sending": ["ECU"],
        "receiving": ["STEER", "BMS_HV"],
        "contents": {
            "current": "uint16",
            "status": ["OFF", "PRECHARGE", "ON", "FATAL"]
        }
    },{
        "name": "ENC_C_FROM_ACU",
        "topic": "A",
        "priority": 7,
        "sending": ["ECU"],
        "receiving": ["STEER", "BMS_HV"],
        "contents": {
            "current": "uint16",
            "status": ["OFF", "PRECHARGE", "ON", "FATAL"]
        }
    },{
        "name": "PEDALS_FROM_ATC",
        "topic": "A",
        "priority": 7,
        "sending": ["ECU"],
        "receiving": ["STEER", "BMS_HV"],
        "contents": {
            "current": "uint16",
            "status": ["OFF", "PRECHARGE", "ON", "FATAL"]
        }
    },{
        "name": "PEDALS_FROM_ACU",
        "topic": "A",
        "priority": 3,
        "sending": ["ECU"],
        "receiving": ["STEER", "BMS_HV"],
        "contents": {
            "current": "uint16",
            "status": ["OFF", "PRECHARGE", "ON", "FATAL"]
        }
    },{
        "name": "HV_VOLT",
        "topic": "B",
        "priority": 7,
        "sending": ["ECU"],
        "receiving": ["STEER", "BMS_HV"],
        "contents": {
            "current": "uint16",
            "status": ["OFF", "PRECHARGE", "ON", "FATAL"]
        }
    },{
        "name": "HV_TEMP",
        "topic": "B",
        "priority": 7,
        "sending": ["ECU"],
        "receiving": ["STEER", "BMS_HV"],
        "contents": {
            "current": "uint16",
            "status": ["OFF", "PRECHARGE", "ON", "FATAL"]
        }
    },{
        "name": "HV_CURR_ERR_WARN",
        "topic": "B",
        "priority": 7,
        "sending": ["ECU"],
        "receiving": ["STEER", "BMS_HV"],
        "contents": {
            "current": "uint16",
            "status": ["OFF", "PRECHARGE", "ON", "FATAL"]
        }
    },{
        "name": "LV_STATUS",
        "topic": "B",
        "priority": 7,
        "sending": ["ECU"],
        "receiving": ["STEER", "BMS_HV"],
        "contents": {
            "current": "uint16",
            "status": ["OFF", "PRECHARGE", "ON", "FATAL"]
        }
    },{
        "name": "LV_STATUS_JUDGE",
        "topic": "B",
        "priority": 6,
        "sending": ["ECU"],
        "receiving": ["STEER", "BMS_HV"],
        "contents": {
            "current": "uint16",
            "status": ["OFF", "PRECHARGE", "ON", "FATAL"]
        }
    },{
        "name": "INV_R_TEMP",
        "topic": "AB",
        "priority": 6,
        "sending": ["ECU"],
        "receiving": ["STEER", "BMS_HV"],
        "contents": {
            "current": "uint16",
            "status": ["OFF", "PRECHARGE", "ON", "FATAL"]
        }
    },{
        "name": "INV_L_TEMP",
        "topic": "AB",
        "priority": 7,
        "sending": ["ECU"],
        "receiving": ["STEER", "BMS_HV"],
        "contents": {
            "current": "uint16",
            "status": ["OFF", "PRECHARGE", "ON", "FATAL"]
        }
    },{
        "name": "MOT_R_TEMP",
        "topic": "AB",
        "priority": 0,
        "sending": ["ECU"],
        "receiving": ["STEER", "BMS_HV"],
        "contents": {
            "current": "uint16",
            "status": ["OFF", "PRECHARGE", "ON", "FATAL"]
        }
    },{
        "name": "MOT_L_TEMP",
        "topic": "AB",
        "priority": 7,
        "sending": ["ECU"],
        "receiving": ["STEER", "BMS_HV"],
        "contents": {
            "current": "uint16",
            "status": ["OFF", "PRECHARGE", "ON", "FATAL"]
        }
    },{
        "name": "CAL_SET_MIN_MAX",
        "topic": "AB",
        "priority": 7,
        "sending": ["ECU"],
        "receiving": ["STEER", "BMS_HV"],
        "contents": {
            "current": "uint16",
            "status": ["OFF", "PRECHARGE", "ON", "FATAL"]
        }
    },{
        "name": "CAL_RESP",
        "topic": "T",
        "priority": 7,
        "sending": ["ECU"],
        "receiving": ["STEER", "BMS_HV"],
        "contents": {
            "current": "uint16",
            "status": ["OFF", "PRECHARGE", "ON", "FATAL"]
        }
    }
 ]
